genimtools-0.0.12.dist-info/METADATA
genimtools-0.0.12.dist-info/WHEEL
genimtools/ailist/__init__.py
genimtools/ailist/__init__.pyi
genimtools/__init__.py
genimtools/utils/__init__.py
genimtools/utils/__init__.pyi
genimtools/vocab/__init__.py
genimtools/vocab/__init__.pyi
genimtools/tokenizers/__init__.py
genimtools/tokenizers/__init__.pyi
genimtools/__init__.pyi
genimtools/genimtools.pypy310-pp73-aarch64-linux-gnu.so
genimtools-0.0.12.dist-info/RECORD
